orangecontrib/__init__.py
orangecontrib/automl/__init__.py
orangecontrib/automl/autogluon.py
orangecontrib/automl/automl_h2o.py
orangecontrib/automl/autosklearn.py
orangecontrib/automl/i18n/Chinese.json
orangecontrib/automl/i18n/Chinese.json.progress.json
orangecontrib/automl/i18n/English.json
orangecontrib/automl/i18n/French.json
orangecontrib/automl/i18n/French.json.progress.json
orangecontrib/automl/i18n/German.json
orangecontrib/automl/i18n/German.json.progress.json
orangecontrib/automl/i18n/Japanese.json
orangecontrib/automl/i18n/Japanese.json.progress.json
orangecontrib/automl/i18n/Korean.json
orangecontrib/automl/i18n/Korean.json.progress.json
orangecontrib/automl/i18n/Polish.json
orangecontrib/automl/i18n/Polish.json.progress.json
orangecontrib/automl/i18n/Slovenian.json
orangecontrib/automl/i18n/Slovenian.json.progress.json
orangecontrib/automl/i18n/Spanish.json
orangecontrib/automl/i18n/Spanish.json.progress.json
orangecontrib/automl/i18n/Thai.json
orangecontrib/automl/i18n/Thai.json.progress.json
orangecontrib/automl/widgets/__init__.py
orangecontrib/automl/widgets/owautogluon.py
orangecontrib/automl/widgets/owautosklearn.py
orangecontrib/automl/widgets/owh2o.py
orangecontrib/automl/widgets/icons/autogluon-logo.svg
orangecontrib/automl/widgets/icons/automl.svg
orangecontrib/automl/widgets/icons/autosklearn-logo.svg
orangecontrib/automl/widgets/icons/h2o-logo.svg
orange3_automl-0.1.3.dist-info/METADATA
orange3_automl-0.1.3.dist-info/WHEEL
orange3_automl-0.1.3.dist-info/entry_points.txt
orange3_automl-0.1.3.dist-info/top_level.txt
orange3_automl-0.1.3.dist-info/RECORD
