Metadata-Version: 2.4
Name: orange3-automl
Version: 0.1.3
Summary: Orange3 add-on for H2O and AutoGluon AutoML Learning.
Author-email: Chris Lee <github@chrislee.dhs.org>
License: CC-BY-NC-SA-4.0
Project-URL: Homepage, https://github.com/chrislee35/orange3-automl
Keywords: orange3 add-on
Classifier: Development Status :: 3 - Alpha
Classifier: Intended Audience :: Education
Classifier: Intended Audience :: Science/Research
Classifier: Programming Language :: Python :: 3 :: Only
Requires-Python: >=3.12
Requires-Dist: Orange3>=3.34.0
Requires-Dist: h2o>=3.44
Requires-Dist: autogluon>=1.4.0
Requires-Dist: auto-sklearn2>=1.0.0
Requires-Dist: xgboost==2.0.2
Provides-Extra: test
Requires-Dist: coverage; extra == "test"
Provides-Extra: doc
Requires-Dist: sphinx; extra == "doc"
Requires-Dist: recommonmark; extra == "doc"
Requires-Dist: sphinx_rtd_theme; extra == "doc"
